wslshot/__init__.py
wslshot/cli.py
wslshot-0.0.12.dist-info/LICENSE
wslshot-0.0.12.dist-info/METADATA
wslshot-0.0.12.dist-info/WHEEL
wslshot-0.0.12.dist-info/entry_points.txt
wslshot-0.0.12.dist-info/top_level.txt
wslshot-0.0.12.dist-info/RECORD
