Metadata-Version: 2.1
Name: wslshot
Version: 0.0.12
Home-page: https://github.com/sderev/wslshot
Author: Sébastien De Revière
License: Apache Licence, Version 2.0
Project-URL: Documentation, https://github.com/sderev/wslshot
Project-URL: Issues, http://github.com/sderev/wslshot/issues
Project-URL: Changelog, https://github.com/sderev/wslshot/releases
Requires-Python: >=3.8
License-File: LICENSE
Requires-Dist: click
Requires-Dist: click-default-group
